{"assets":{"74BED5C01827A0250686C62E0B6C4FBC":{"type":"texture","index":3,"assetRequest":{"type":"slide","state":"contents","slide":"none"},"url":{"native":"assets\/951BCDA2-1682-4349-9C54-E2EA6F9D097A.pdf"},"width":601,"height":55},"8E39EA93C958539EDD133FF73DC82887":{"type":"texture","index":2,"assetRequest":{"type":"slide","state":"contents","slide":"none"},"url":{"native":"assets\/951BCDA2-1682-4349-9C54-E2EA6F9D097A.pdf"},"width":175,"height":55},"E919CCB980446EFCFE6CA0B1FA473AF5":{"type":"texture","index":5,"assetRequest":{"type":"slide","state":"contents","slide":"none"},"url":{"native":"assets\/951BCDA2-1682-4349-9C54-E2EA6F9D097A.pdf"},"width":456,"height":55},"C57C769CF9D7B954C9ABBCAAAD5B84D8":{"type":"texture","index":6,"assetRequest":{"type":"slide","state":"contents","slide":"none"},"url":{"native":"assets\/951BCDA2-1682-4349-9C54-E2EA6F9D097A.pdf"},"width":1024,"height":768},"DB8451458D98EFA7506DBEBC2B1323F0":{"type":"texture","index":0,"assetRequest":{"type":"slide","state":"contents","slide":"none"},"url":{"native":"assets\/951BCDA2-1682-4349-9C54-E2EA6F9D097A.pdf"},"width":1024,"height":768},"5B29C2D90D4343C3E8B5BF98D3595A21":{"type":"texture","index":1,"assetRequest":{"type":"slide","state":"contents","slide":"none"},"url":{"native":"assets\/951BCDA2-1682-4349-9C54-E2EA6F9D097A.pdf"},"width":864,"height":140},"A7867212BDDC5550EBCA458AE2DD33BC":{"type":"texture","index":4,"assetRequest":{"type":"slide","state":"contents","slide":"none"},"url":{"native":"assets\/951BCDA2-1682-4349-9C54-E2EA6F9D097A.pdf"},"width":708,"height":55},"7BA44EE4C83848934E09B512DF4E5631":{"type":"texture","index":7,"assetRequest":{"type":"slide","state":"contents","slide":"none"},"url":{"native":"assets\/951BCDA2-1682-4349-9C54-E2EA6F9D097A.pdf"},"width":1024,"height":768}},"events":[{"effects":[{"beginTime":0,"baseLayer":{"animations":[],"initialState":{"affineTransform":[1,0,0,1,0,0],"masksToBounds":false,"rotation":0,"scale":1,"position":{"pointX":446.5,"pointY":351.5},"width":743,"sublayerTransform":[1,0,0,0,0,1,0,0,0,0,1,0,0,0,0,1],"contentsRect":{"y":0,"x":0,"width":1,"height":1},"opacity":1,"edgeAntialiasingMask":251658240,"height":295,"hidden":false,"anchorPoint":{"pointX":0.5,"pointY":0.5}},"objectID":"F9E39735-38FD-46FE-ACE0-B70E2A7C8901","layers":[{"animations":[],"initialState":{"affineTransform":[1,0,0,1,0,0],"masksToBounds":false,"rotation":0,"scale":1,"position":{"pointX":437,"pointY":180},"width":743,"sublayerTransform":[1,0,0,0,0,1,0,0,0,0,1,-0.00049229876906403734,0,0,0,1],"contentsRect":{"y":0,"x":0,"width":1,"height":1},"opacity":1,"edgeAntialiasingMask":251658240,"height":295,"hidden":false,"anchorPoint":{"pointX":0.58815612382234184,"pointY":0.61016949152542377}},"layers":[{"animations":[{"timeOffset":0,"from":{"scalar":true},"beginTime":1e-100,"repeatCount":0,"fillMode":"both","property":"hidden","autoreverses":false,"duration":0.01,"to":{"scalar":false}}],"layers":[],"texturedRectangle":{"singleTextureOpacity":1,"textXHeight":0.30080000000000001,"textBaseline":0.71432883522727275,"isBackgroundTexture":false,"isVerticalText":false,"textColor":[0.9999966025352478,0.99999994039535522,0.99999994039535522,1],"textureType":6},"initialState":{"affineTransform":[1,0,0,1,0,0],"masksToBounds":false,"rotation":0,"scale":1,"position":{"pointX":91.5,"pointY":127.5},"width":175,"sublayerTransform":[1,0,0,0,0,1,0,0,0,0,1,0,0,0,0,1],"contentsRect":{"y":0,"x":0,"width":1,"height":1},"opacity":1,"edgeAntialiasingMask":0,"height":55,"hidden":true,"anchorPoint":{"pointX":0.5,"pointY":0.5}},"texture":"8E39EA93C958539EDD133FF73DC82887"}]},{"animations":[],"layers":[],"texturedRectangle":{"singleTextureOpacity":1,"textXHeight":0.30080000000000001,"textBaseline":0.71432883522727275,"isBackgroundTexture":false,"isVerticalText":false,"textColor":[0.9999966025352478,0.99999994039535522,0.99999994039535522,1],"textureType":6},"initialState":{"affineTransform":[1,0,0,1,0,0],"masksToBounds":false,"rotation":0,"scale":1,"position":{"pointX":339.5,"pointY":207.5},"width":601,"sublayerTransform":[1,0,0,0,0,1,0,0,0,0,1,0,0,0,0,1],"contentsRect":{"y":0,"x":0,"width":1,"height":1},"opacity":1,"edgeAntialiasingMask":0,"height":55,"hidden":true,"anchorPoint":{"pointX":0.5,"pointY":0.5}},"texture":"74BED5C01827A0250686C62E0B6C4FBC"},{"animations":[],"layers":[],"texturedRectangle":{"singleTextureOpacity":1,"textXHeight":0.30080000000000001,"textBaseline":0.71432883522727275,"isBackgroundTexture":false,"isVerticalText":false,"textColor":[0.9999966025352478,0.99999994039535522,0.99999994039535522,1],"textureType":6},"initialState":{"affineTransform":[1,0,0,1,0,0],"masksToBounds":false,"rotation":0,"scale":1,"position":{"pointX":393,"pointY":287.5},"width":708,"sublayerTransform":[1,0,0,0,0,1,0,0,0,0,1,0,0,0,0,1],"contentsRect":{"y":0,"x":0,"width":1,"height":1},"opacity":1,"edgeAntialiasingMask":0,"height":55,"hidden":true,"anchorPoint":{"pointX":0.5,"pointY":0.5}},"texture":"A7867212BDDC5550EBCA458AE2DD33BC"},{"animations":[],"layers":[],"texturedRectangle":{"singleTextureOpacity":1,"textXHeight":0.30080000000000001,"textBaseline":0.71432883522727275,"isBackgroundTexture":false,"isVerticalText":false,"textColor":[0.9999966025352478,0.99999994039535522,0.99999994039535522,1],"textureType":6},"initialState":{"affineTransform":[1,0,0,1,0,0],"masksToBounds":false,"rotation":0,"scale":1,"position":{"pointX":267,"pointY":367.5},"width":456,"sublayerTransform":[1,0,0,0,0,1,0,0,0,0,1,0,0,0,0,1],"contentsRect":{"y":0,"x":0,"width":1,"height":1},"opacity":1,"edgeAntialiasingMask":0,"height":55,"hidden":true,"anchorPoint":{"pointX":0.5,"pointY":0.5}},"texture":"E919CCB980446EFCFE6CA0B1FA473AF5"}]},"effects":[],"duration":0.01,"type":"buildIn","name":"apple:appear","objectID":"F9E39735-38FD-46FE-ACE0-B70E2A7C8901"}],"automaticPlay":false,"hyperlinks":[],"accessibility":[{"text":"Ok, so you’re still determined to tamper with blocks.","targetRectangle":{"y":28,"x":80.383999999999901,"width":881.02400000000023,"height":154.1435546875}}],"baseLayer":{"animations":[],"initialState":{"affineTransform":[1,0,0,1,0,0],"masksToBounds":false,"rotation":0,"scale":1,"position":{"pointX":512,"pointY":384},"width":1024,"sublayerTransform":[1,0,0,0,0,1,0,0,0,0,1,0,0,0,0,1],"contentsRect":{"y":0,"x":0,"width":1,"height":1},"opacity":1,"edgeAntialiasingMask":251658240,"height":768,"hidden":false,"anchorPoint":{"pointX":0.5,"pointY":0.5}},"layers":[{"animations":[],"initialState":{"affineTransform":[1,0,0,1,0,0],"masksToBounds":false,"rotation":0,"scale":1,"position":{"pointX":512,"pointY":384},"width":1024,"sublayerTransform":[1,0,0,0,0,1,0,0,0,0,1,0,0,0,0,1],"contentsRect":{"y":0,"x":0,"width":1,"height":1},"opacity":1,"edgeAntialiasingMask":251658240,"height":768,"hidden":false,"anchorPoint":{"pointX":0.5,"pointY":0.5}},"layers":[{"animations":[],"initialState":{"affineTransform":[1,0,0,1,0,0],"masksToBounds":false,"rotation":0,"scale":1,"position":{"pointX":512,"pointY":384},"width":1024,"sublayerTransform":[1,0,0,0,0,1,0,0,0,0,1,0,0,0,0,1],"contentsRect":{"y":0,"x":0,"width":1,"height":1},"opacity":1,"edgeAntialiasingMask":251658240,"height":768,"hidden":false,"anchorPoint":{"pointX":0.5,"pointY":0.5}},"layers":[{"animations":[],"layers":[],"texturedRectangle":{"isBackgroundTexture":true,"singleTextureOpacity":1,"textureType":1,"textBaseline":0,"textXHeight":0,"isVerticalText":false},"initialState":{"affineTransform":[1,0,0,1,0,0],"masksToBounds":false,"rotation":0,"scale":1,"position":{"pointX":512,"pointY":384},"width":1024,"sublayerTransform":[1,0,0,0,0,1,0,0,0,0,1,0,0,0,0,1],"contentsRect":{"y":0,"x":0,"width":1,"height":1},"opacity":1,"edgeAntialiasingMask":0,"height":768,"hidden":false,"anchorPoint":{"pointX":0.5,"pointY":0.5}},"texture":"DB8451458D98EFA7506DBEBC2B1323F0"}]}]},{"animations":[],"initialState":{"affineTransform":[1,0,0,1,0,0],"masksToBounds":false,"rotation":0,"scale":1,"position":{"pointX":512,"pointY":384},"width":1024,"sublayerTransform":[1,0,0,0,0,1,0,0,0,0,1,0,0,0,0,1],"contentsRect":{"y":0,"x":0,"width":1,"height":1},"opacity":1,"edgeAntialiasingMask":251658240,"height":768,"hidden":false,"anchorPoint":{"pointX":0.5,"pointY":0.5}},"layers":[{"animations":[],"initialState":{"affineTransform":[1,0,0,1,0,0],"masksToBounds":false,"rotation":0,"scale":1,"position":{"pointX":507,"pointY":90},"width":864,"sublayerTransform":[1,0,0,0,0,1,0,0,0,0,1,0,0,0,0,1],"contentsRect":{"y":0,"x":0,"width":1,"height":1},"opacity":1,"edgeAntialiasingMask":251658240,"height":140,"hidden":false,"anchorPoint":{"pointX":0.5,"pointY":0.5}},"layers":[{"animations":[],"layers":[],"texturedRectangle":{"singleTextureOpacity":1,"textXHeight":0.23634285714285716,"textBaseline":0.90182756696428568,"isBackgroundTexture":true,"isVerticalText":false,"textColor":[0.9999966025352478,0.99999994039535522,0.99999994039535522,1],"textureType":6},"initialState":{"affineTransform":[1,0,0,1,0,0],"masksToBounds":false,"rotation":0,"scale":1,"position":{"pointX":438,"pointY":92},"width":864,"sublayerTransform":[1,0,0,0,0,1,0,0,0,0,1,0,0,0,0,1],"contentsRect":{"y":0,"x":0,"width":1,"height":1},"opacity":1,"edgeAntialiasingMask":0,"height":140,"hidden":false,"anchorPoint":{"pointX":0.5,"pointY":0.5}},"texture":"5B29C2D90D4343C3E8B5BF98D3595A21"}]}]},{"animations":[],"initialState":{"affineTransform":[1,0,0,1,0,0],"masksToBounds":false,"rotation":0,"scale":1,"position":{"pointX":512,"pointY":384},"width":1024,"sublayerTransform":[1,0,0,0,0,1,0,0,0,0,1,0,0,0,0,1],"contentsRect":{"y":0,"x":0,"width":1,"height":1},"opacity":1,"edgeAntialiasingMask":251658240,"height":768,"hidden":false,"anchorPoint":{"pointX":0.5,"pointY":0.5}},"layers":[{"animations":[],"initialState":{"affineTransform":[1,0,0,1,0,0],"masksToBounds":false,"rotation":0,"scale":1,"position":{"pointX":446.5,"pointY":351.5},"width":743,"sublayerTransform":[1,0,0,0,0,1,0,0,0,0,1,0,0,0,0,1],"contentsRect":{"y":0,"x":0,"width":1,"height":1},"opacity":1,"edgeAntialiasingMask":251658240,"height":295,"hidden":false,"anchorPoint":{"pointX":0.5,"pointY":0.5}},"objectID":"F9E39735-38FD-46FE-ACE0-B70E2A7C8901","layers":[{"animations":[],"layers":[],"texturedRectangle":{"singleTextureOpacity":1,"textXHeight":0.30080000000000001,"textBaseline":0.71432883522727275,"isBackgroundTexture":false,"isVerticalText":false,"textColor":[0.9999966025352478,0.99999994039535522,0.99999994039535522,1],"textureType":6},"initialState":{"affineTransform":[1,0,0,1,0,0],"masksToBounds":false,"rotation":0,"scale":1,"position":{"pointX":91.5,"pointY":127.5},"width":175,"sublayerTransform":[1,0,0,0,0,1,0,0,0,0,1,0,0,0,0,1],"contentsRect":{"y":0,"x":0,"width":1,"height":1},"opacity":1,"edgeAntialiasingMask":0,"height":55,"hidden":true,"anchorPoint":{"pointX":0.5,"pointY":0.5}},"texture":"8E39EA93C958539EDD133FF73DC82887"},{"animations":[],"layers":[],"texturedRectangle":{"singleTextureOpacity":1,"textXHeight":0.30080000000000001,"textBaseline":0.71432883522727275,"isBackgroundTexture":false,"isVerticalText":false,"textColor":[0.9999966025352478,0.99999994039535522,0.99999994039535522,1],"textureType":6},"initialState":{"affineTransform":[1,0,0,1,0,0],"masksToBounds":false,"rotation":0,"scale":1,"position":{"pointX":339.5,"pointY":207.5},"width":601,"sublayerTransform":[1,0,0,0,0,1,0,0,0,0,1,0,0,0,0,1],"contentsRect":{"y":0,"x":0,"width":1,"height":1},"opacity":1,"edgeAntialiasingMask":0,"height":55,"hidden":true,"anchorPoint":{"pointX":0.5,"pointY":0.5}},"texture":"74BED5C01827A0250686C62E0B6C4FBC"},{"animations":[],"layers":[],"texturedRectangle":{"singleTextureOpacity":1,"textXHeight":0.30080000000000001,"textBaseline":0.71432883522727275,"isBackgroundTexture":false,"isVerticalText":false,"textColor":[0.9999966025352478,0.99999994039535522,0.99999994039535522,1],"textureType":6},"initialState":{"affineTransform":[1,0,0,1,0,0],"masksToBounds":false,"rotation":0,"scale":1,"position":{"pointX":393,"pointY":287.5},"width":708,"sublayerTransform":[1,0,0,0,0,1,0,0,0,0,1,0,0,0,0,1],"contentsRect":{"y":0,"x":0,"width":1,"height":1},"opacity":1,"edgeAntialiasingMask":0,"height":55,"hidden":true,"anchorPoint":{"pointX":0.5,"pointY":0.5}},"texture":"A7867212BDDC5550EBCA458AE2DD33BC"},{"animations":[],"layers":[],"texturedRectangle":{"singleTextureOpacity":1,"textXHeight":0.30080000000000001,"textBaseline":0.71432883522727275,"isBackgroundTexture":false,"isVerticalText":false,"textColor":[0.9999966025352478,0.99999994039535522,0.99999994039535522,1],"textureType":6},"initialState":{"affineTransform":[1,0,0,1,0,0],"masksToBounds":false,"rotation":0,"scale":1,"position":{"pointX":267,"pointY":367.5},"width":456,"sublayerTransform":[1,0,0,0,0,1,0,0,0,0,1,0,0,0,0,1],"contentsRect":{"y":0,"x":0,"width":1,"height":1},"opacity":1,"edgeAntialiasingMask":0,"height":55,"hidden":true,"anchorPoint":{"pointX":0.5,"pointY":0.5}},"texture":"E919CCB980446EFCFE6CA0B1FA473AF5"}]}]}]}},{"effects":[{"beginTime":0,"baseLayer":{"animations":[],"initialState":{"affineTransform":[1,0,0,1,0,0],"masksToBounds":false,"rotation":0,"scale":1,"position":{"pointX":446.5,"pointY":351.5},"width":743,"sublayerTransform":[1,0,0,0,0,1,0,0,0,0,1,0,0,0,0,1],"contentsRect":{"y":0,"x":0,"width":1,"height":1},"opacity":1,"edgeAntialiasingMask":251658240,"height":295,"hidden":false,"anchorPoint":{"pointX":0.5,"pointY":0.5}},"objectID":"F9E39735-38FD-46FE-ACE0-B70E2A7C8901","layers":[{"animations":[],"layers":[],"texturedRectangle":{"singleTextureOpacity":1,"textXHeight":0.30080000000000001,"textBaseline":0.71432883522727275,"isBackgroundTexture":false,"isVerticalText":false,"textColor":[0.9999966025352478,0.99999994039535522,0.99999994039535522,1],"textureType":6},"initialState":{"affineTransform":[1,0,0,1,0,0],"masksToBounds":false,"rotation":0,"scale":1,"position":{"pointX":91.5,"pointY":127.5},"width":175,"sublayerTransform":[1,0,0,0,0,1,0,0,0,0,1,0,0,0,0,1],"contentsRect":{"y":0,"x":0,"width":1,"height":1},"opacity":1,"edgeAntialiasingMask":0,"height":55,"hidden":false,"anchorPoint":{"pointX":0.5,"pointY":0.5}},"texture":"8E39EA93C958539EDD133FF73DC82887"},{"animations":[],"initialState":{"affineTransform":[1,0,0,1,0,0],"masksToBounds":false,"rotation":0,"scale":1,"position":{"pointX":437,"pointY":180},"width":743,"sublayerTransform":[1,0,0,0,0,1,0,0,0,0,1,-0.00049229876906403734,0,0,0,1],"contentsRect":{"y":0,"x":0,"width":1,"height":1},"opacity":1,"edgeAntialiasingMask":251658240,"height":295,"hidden":false,"anchorPoint":{"pointX":0.58815612382234184,"pointY":0.61016949152542377}},"layers":[{"animations":[{"timeOffset":0,"from":{"scalar":true},"beginTime":1e-100,"repeatCount":0,"fillMode":"both","property":"hidden","autoreverses":false,"duration":0.01,"to":{"scalar":false}}],"layers":[],"texturedRectangle":{"singleTextureOpacity":1,"textXHeight":0.30080000000000001,"textBaseline":0.71432883522727275,"isBackgroundTexture":false,"isVerticalText":false,"textColor":[0.9999966025352478,0.99999994039535522,0.99999994039535522,1],"textureType":6},"initialState":{"affineTransform":[1,0,0,1,0,0],"masksToBounds":false,"rotation":0,"scale":1,"position":{"pointX":339.5,"pointY":207.5},"width":601,"sublayerTransform":[1,0,0,0,0,1,0,0,0,0,1,0,0,0,0,1],"contentsRect":{"y":0,"x":0,"width":1,"height":1},"opacity":1,"edgeAntialiasingMask":0,"height":55,"hidden":true,"anchorPoint":{"pointX":0.5,"pointY":0.5}},"texture":"74BED5C01827A0250686C62E0B6C4FBC"}]},{"animations":[],"layers":[],"texturedRectangle":{"singleTextureOpacity":1,"textXHeight":0.30080000000000001,"textBaseline":0.71432883522727275,"isBackgroundTexture":false,"isVerticalText":false,"textColor":[0.9999966025352478,0.99999994039535522,0.99999994039535522,1],"textureType":6},"initialState":{"affineTransform":[1,0,0,1,0,0],"masksToBounds":false,"rotation":0,"scale":1,"position":{"pointX":393,"pointY":287.5},"width":708,"sublayerTransform":[1,0,0,0,0,1,0,0,0,0,1,0,0,0,0,1],"contentsRect":{"y":0,"x":0,"width":1,"height":1},"opacity":1,"edgeAntialiasingMask":0,"height":55,"hidden":true,"anchorPoint":{"pointX":0.5,"pointY":0.5}},"texture":"A7867212BDDC5550EBCA458AE2DD33BC"},{"animations":[],"layers":[],"texturedRectangle":{"singleTextureOpacity":1,"textXHeight":0.30080000000000001,"textBaseline":0.71432883522727275,"isBackgroundTexture":false,"isVerticalText":false,"textColor":[0.9999966025352478,0.99999994039535522,0.99999994039535522,1],"textureType":6},"initialState":{"affineTransform":[1,0,0,1,0,0],"masksToBounds":false,"rotation":0,"scale":1,"position":{"pointX":267,"pointY":367.5},"width":456,"sublayerTransform":[1,0,0,0,0,1,0,0,0,0,1,0,0,0,0,1],"contentsRect":{"y":0,"x":0,"width":1,"height":1},"opacity":1,"edgeAntialiasingMask":0,"height":55,"hidden":true,"anchorPoint":{"pointX":0.5,"pointY":0.5}},"texture":"E919CCB980446EFCFE6CA0B1FA473AF5"}]},"effects":[],"duration":0.01,"type":"buildIn","name":"apple:appear","objectID":"F9E39735-38FD-46FE-ACE0-B70E2A7C8901"}],"automaticPlay":false,"hyperlinks":[],"accessibility":[{"text":"Ok, so you’re still determined to tamper with blocks.","targetRectangle":{"y":28,"x":80.383999999999901,"width":881.02400000000023,"height":154.1435546875}},{"text":"Checklist:","targetRectangle":{"y":313,"x":114,"width":141.05599999999998,"height":37.10400390625}}],"baseLayer":{"animations":[],"initialState":{"affineTransform":[1,0,0,1,0,0],"masksToBounds":false,"rotation":0,"scale":1,"position":{"pointX":512,"pointY":384},"width":1024,"sublayerTransform":[1,0,0,0,0,1,0,0,0,0,1,0,0,0,0,1],"contentsRect":{"y":0,"x":0,"width":1,"height":1},"opacity":1,"edgeAntialiasingMask":251658240,"height":768,"hidden":false,"anchorPoint":{"pointX":0.5,"pointY":0.5}},"layers":[{"animations":[],"initialState":{"affineTransform":[1,0,0,1,0,0],"masksToBounds":false,"rotation":0,"scale":1,"position":{"pointX":512,"pointY":384},"width":1024,"sublayerTransform":[1,0,0,0,0,1,0,0,0,0,1,0,0,0,0,1],"contentsRect":{"y":0,"x":0,"width":1,"height":1},"opacity":1,"edgeAntialiasingMask":251658240,"height":768,"hidden":false,"anchorPoint":{"pointX":0.5,"pointY":0.5}},"layers":[{"animations":[],"initialState":{"affineTransform":[1,0,0,1,0,0],"masksToBounds":false,"rotation":0,"scale":1,"position":{"pointX":512,"pointY":384},"width":1024,"sublayerTransform":[1,0,0,0,0,1,0,0,0,0,1,0,0,0,0,1],"contentsRect":{"y":0,"x":0,"width":1,"height":1},"opacity":1,"edgeAntialiasingMask":251658240,"height":768,"hidden":false,"anchorPoint":{"pointX":0.5,"pointY":0.5}},"layers":[{"animations":[],"layers":[],"texturedRectangle":{"isBackgroundTexture":true,"singleTextureOpacity":1,"textureType":1,"textBaseline":0,"textXHeight":0,"isVerticalText":false},"initialState":{"affineTransform":[1,0,0,1,0,0],"masksToBounds":false,"rotation":0,"scale":1,"position":{"pointX":512,"pointY":384},"width":1024,"sublayerTransform":[1,0,0,0,0,1,0,0,0,0,1,0,0,0,0,1],"contentsRect":{"y":0,"x":0,"width":1,"height":1},"opacity":1,"edgeAntialiasingMask":0,"height":768,"hidden":false,"anchorPoint":{"pointX":0.5,"pointY":0.5}},"texture":"DB8451458D98EFA7506DBEBC2B1323F0"}]}]},{"animations":[],"initialState":{"affineTransform":[1,0,0,1,0,0],"masksToBounds":false,"rotation":0,"scale":1,"position":{"pointX":512,"pointY":384},"width":1024,"sublayerTransform":[1,0,0,0,0,1,0,0,0,0,1,0,0,0,0,1],"contentsRect":{"y":0,"x":0,"width":1,"height":1},"opacity":1,"edgeAntialiasingMask":251658240,"height":768,"hidden":false,"anchorPoint":{"pointX":0.5,"pointY":0.5}},"layers":[{"animations":[],"initialState":{"affineTransform":[1,0,0,1,0,0],"masksToBounds":false,"rotation":0,"scale":1,"position":{"pointX":507,"pointY":90},"width":864,"sublayerTransform":[1,0,0,0,0,1,0,0,0,0,1,0,0,0,0,1],"contentsRect":{"y":0,"x":0,"width":1,"height":1},"opacity":1,"edgeAntialiasingMask":251658240,"height":140,"hidden":false,"anchorPoint":{"pointX":0.5,"pointY":0.5}},"layers":[{"animations":[],"layers":[],"texturedRectangle":{"singleTextureOpacity":1,"textXHeight":0.23634285714285716,"textBaseline":0.90182756696428568,"isBackgroundTexture":true,"isVerticalText":false,"textColor":[0.9999966025352478,0.99999994039535522,0.99999994039535522,1],"textureType":6},"initialState":{"affineTransform":[1,0,0,1,0,0],"masksToBounds":false,"rotation":0,"scale":1,"position":{"pointX":438,"pointY":92},"width":864,"sublayerTransform":[1,0,0,0,0,1,0,0,0,0,1,0,0,0,0,1],"contentsRect":{"y":0,"x":0,"width":1,"height":1},"opacity":1,"edgeAntialiasingMask":0,"height":140,"hidden":false,"anchorPoint":{"pointX":0.5,"pointY":0.5}},"texture":"5B29C2D90D4343C3E8B5BF98D3595A21"}]}]},{"animations":[],"initialState":{"affineTransform":[1,0,0,1,0,0],"masksToBounds":false,"rotation":0,"scale":1,"position":{"pointX":512,"pointY":384},"width":1024,"sublayerTransform":[1,0,0,0,0,1,0,0,0,0,1,0,0,0,0,1],"contentsRect":{"y":0,"x":0,"width":1,"height":1},"opacity":1,"edgeAntialiasingMask":251658240,"height":768,"hidden":false,"anchorPoint":{"pointX":0.5,"pointY":0.5}},"layers":[{"animations":[],"initialState":{"affineTransform":[1,0,0,1,0,0],"masksToBounds":false,"rotation":0,"scale":1,"position":{"pointX":446.5,"pointY":351.5},"width":743,"sublayerTransform":[1,0,0,0,0,1,0,0,0,0,1,0,0,0,0,1],"contentsRect":{"y":0,"x":0,"width":1,"height":1},"opacity":1,"edgeAntialiasingMask":251658240,"height":295,"hidden":false,"anchorPoint":{"pointX":0.5,"pointY":0.5}},"objectID":"F9E39735-38FD-46FE-ACE0-B70E2A7C8901","layers":[{"animations":[],"layers":[],"texturedRectangle":{"singleTextureOpacity":1,"textXHeight":0.30080000000000001,"textBaseline":0.71432883522727275,"isBackgroundTexture":false,"isVerticalText":false,"textColor":[0.9999966025352478,0.99999994039535522,0.99999994039535522,1],"textureType":6},"initialState":{"affineTransform":[1,0,0,1,0,0],"masksToBounds":false,"rotation":0,"scale":1,"position":{"pointX":91.5,"pointY":127.5},"width":175,"sublayerTransform":[1,0,0,0,0,1,0,0,0,0,1,0,0,0,0,1],"contentsRect":{"y":0,"x":0,"width":1,"height":1},"opacity":1,"edgeAntialiasingMask":0,"height":55,"hidden":false,"anchorPoint":{"pointX":0.5,"pointY":0.5}},"texture":"8E39EA93C958539EDD133FF73DC82887"},{"animations":[],"layers":[],"texturedRectangle":{"singleTextureOpacity":1,"textXHeight":0.30080000000000001,"textBaseline":0.71432883522727275,"isBackgroundTexture":false,"isVerticalText":false,"textColor":[0.9999966025352478,0.99999994039535522,0.99999994039535522,1],"textureType":6},"initialState":{"affineTransform":[1,0,0,1,0,0],"masksToBounds":false,"rotation":0,"scale":1,"position":{"pointX":339.5,"pointY":207.5},"width":601,"sublayerTransform":[1,0,0,0,0,1,0,0,0,0,1,0,0,0,0,1],"contentsRect":{"y":0,"x":0,"width":1,"height":1},"opacity":1,"edgeAntialiasingMask":0,"height":55,"hidden":true,"anchorPoint":{"pointX":0.5,"pointY":0.5}},"texture":"74BED5C01827A0250686C62E0B6C4FBC"},{"animations":[],"layers":[],"texturedRectangle":{"singleTextureOpacity":1,"textXHeight":0.30080000000000001,"textBaseline":0.71432883522727275,"isBackgroundTexture":false,"isVerticalText":false,"textColor":[0.9999966025352478,0.99999994039535522,0.99999994039535522,1],"textureType":6},"initialState":{"affineTransform":[1,0,0,1,0,0],"masksToBounds":false,"rotation":0,"scale":1,"position":{"pointX":393,"pointY":287.5},"width":708,"sublayerTransform":[1,0,0,0,0,1,0,0,0,0,1,0,0,0,0,1],"contentsRect":{"y":0,"x":0,"width":1,"height":1},"opacity":1,"edgeAntialiasingMask":0,"height":55,"hidden":true,"anchorPoint":{"pointX":0.5,"pointY":0.5}},"texture":"A7867212BDDC5550EBCA458AE2DD33BC"},{"animations":[],"layers":[],"texturedRectangle":{"singleTextureOpacity":1,"textXHeight":0.30080000000000001,"textBaseline":0.71432883522727275,"isBackgroundTexture":false,"isVerticalText":false,"textColor":[0.9999966025352478,0.99999994039535522,0.99999994039535522,1],"textureType":6},"initialState":{"affineTransform":[1,0,0,1,0,0],"masksToBounds":false,"rotation":0,"scale":1,"position":{"pointX":267,"pointY":367.5},"width":456,"sublayerTransform":[1,0,0,0,0,1,0,0,0,0,1,0,0,0,0,1],"contentsRect":{"y":0,"x":0,"width":1,"height":1},"opacity":1,"edgeAntialiasingMask":0,"height":55,"hidden":true,"anchorPoint":{"pointX":0.5,"pointY":0.5}},"texture":"E919CCB980446EFCFE6CA0B1FA473AF5"}]}]}]}},{"effects":[{"beginTime":0,"baseLayer":{"animations":[],"initialState":{"affineTransform":[1,0,0,1,0,0],"masksToBounds":false,"rotation":0,"scale":1,"position":{"pointX":446.5,"pointY":351.5},"width":743,"sublayerTransform":[1,0,0,0,0,1,0,0,0,0,1,0,0,0,0,1],"contentsRect":{"y":0,"x":0,"width":1,"height":1},"opacity":1,"edgeAntialiasingMask":251658240,"height":295,"hidden":false,"anchorPoint":{"pointX":0.5,"pointY":0.5}},"objectID":"F9E39735-38FD-46FE-ACE0-B70E2A7C8901","layers":[{"animations":[],"layers":[],"texturedRectangle":{"singleTextureOpacity":1,"textXHeight":0.30080000000000001,"textBaseline":0.71432883522727275,"isBackgroundTexture":false,"isVerticalText":false,"textColor":[0.9999966025352478,0.99999994039535522,0.99999994039535522,1],"textureType":6},"initialState":{"affineTransform":[1,0,0,1,0,0],"masksToBounds":false,"rotation":0,"scale":1,"position":{"pointX":91.5,"pointY":127.5},"width":175,"sublayerTransform":[1,0,0,0,0,1,0,0,0,0,1,0,0,0,0,1],"contentsRect":{"y":0,"x":0,"width":1,"height":1},"opacity":1,"edgeAntialiasingMask":0,"height":55,"hidden":false,"anchorPoint":{"pointX":0.5,"pointY":0.5}},"texture":"8E39EA93C958539EDD133FF73DC82887"},{"animations":[],"layers":[],"texturedRectangle":{"singleTextureOpacity":1,"textXHeight":0.30080000000000001,"textBaseline":0.71432883522727275,"isBackgroundTexture":false,"isVerticalText":false,"textColor":[0.9999966025352478,0.99999994039535522,0.99999994039535522,1],"textureType":6},"initialState":{"affineTransform":[1,0,0,1,0,0],"masksToBounds":false,"rotation":0,"scale":1,"position":{"pointX":339.5,"pointY":207.5},"width":601,"sublayerTransform":[1,0,0,0,0,1,0,0,0,0,1,0,0,0,0,1],"contentsRect":{"y":0,"x":0,"width":1,"height":1},"opacity":1,"edgeAntialiasingMask":0,"height":55,"hidden":false,"anchorPoint":{"pointX":0.5,"pointY":0.5}},"texture":"74BED5C01827A0250686C62E0B6C4FBC"},{"animations":[],"initialState":{"affineTransform":[1,0,0,1,0,0],"masksToBounds":false,"rotation":0,"scale":1,"position":{"pointX":437,"pointY":180},"width":743,"sublayerTransform":[1,0,0,0,0,1,0,0,0,0,1,-0.00049229876906403734,0,0,0,1],"contentsRect":{"y":0,"x":0,"width":1,"height":1},"opacity":1,"edgeAntialiasingMask":251658240,"height":295,"hidden":false,"anchorPoint":{"pointX":0.58815612382234184,"pointY":0.61016949152542377}},"layers":[{"animations":[{"timeOffset":0,"from":{"scalar":true},"beginTime":1e-100,"repeatCount":0,"fillMode":"both","property":"hidden","autoreverses":false,"duration":0.01,"to":{"scalar":false}}],"layers":[],"texturedRectangle":{"singleTextureOpacity":1,"textXHeight":0.30080000000000001,"textBaseline":0.71432883522727275,"isBackgroundTexture":false,"isVerticalText":false,"textColor":[0.9999966025352478,0.99999994039535522,0.99999994039535522,1],"textureType":6},"initialState":{"affineTransform":[1,0,0,1,0,0],"masksToBounds":false,"rotation":0,"scale":1,"position":{"pointX":393,"pointY":287.5},"width":708,"sublayerTransform":[1,0,0,0,0,1,0,0,0,0,1,0,0,0,0,1],"contentsRect":{"y":0,"x":0,"width":1,"height":1},"opacity":1,"edgeAntialiasingMask":0,"height":55,"hidden":true,"anchorPoint":{"pointX":0.5,"pointY":0.5}},"texture":"A7867212BDDC5550EBCA458AE2DD33BC"}]},{"animations":[],"layers":[],"texturedRectangle":{"singleTextureOpacity":1,"textXHeight":0.30080000000000001,"textBaseline":0.71432883522727275,"isBackgroundTexture":false,"isVerticalText":false,"textColor":[0.9999966025352478,0.99999994039535522,0.99999994039535522,1],"textureType":6},"initialState":{"affineTransform":[1,0,0,1,0,0],"masksToBounds":false,"rotation":0,"scale":1,"position":{"pointX":267,"pointY":367.5},"width":456,"sublayerTransform":[1,0,0,0,0,1,0,0,0,0,1,0,0,0,0,1],"contentsRect":{"y":0,"x":0,"width":1,"height":1},"opacity":1,"edgeAntialiasingMask":0,"height":55,"hidden":true,"anchorPoint":{"pointX":0.5,"pointY":0.5}},"texture":"E919CCB980446EFCFE6CA0B1FA473AF5"}]},"effects":[],"duration":0.01,"type":"buildIn","name":"apple:appear","objectID":"F9E39735-38FD-46FE-ACE0-B70E2A7C8901"}],"automaticPlay":false,"hyperlinks":[],"accessibility":[{"text":"Ok, so you’re still determined to tamper with blocks.","targetRectangle":{"y":28,"x":80.383999999999901,"width":881.02400000000023,"height":154.1435546875}},{"text":"Checklist:","targetRectangle":{"y":313,"x":114,"width":141.05599999999998,"height":37.10400390625}},{"text":"Fix all the chains (calculate hash codes)","targetRectangle":{"y":351,"x":149,"width":565.98400000000015,"height":79.10400390625}}],"baseLayer":{"animations":[],"initialState":{"affineTransform":[1,0,0,1,0,0],"masksToBounds":false,"rotation":0,"scale":1,"position":{"pointX":512,"pointY":384},"width":1024,"sublayerTransform":[1,0,0,0,0,1,0,0,0,0,1,0,0,0,0,1],"contentsRect":{"y":0,"x":0,"width":1,"height":1},"opacity":1,"edgeAntialiasingMask":251658240,"height":768,"hidden":false,"anchorPoint":{"pointX":0.5,"pointY":0.5}},"layers":[{"animations":[],"initialState":{"affineTransform":[1,0,0,1,0,0],"masksToBounds":false,"rotation":0,"scale":1,"position":{"pointX":512,"pointY":384},"width":1024,"sublayerTransform":[1,0,0,0,0,1,0,0,0,0,1,0,0,0,0,1],"contentsRect":{"y":0,"x":0,"width":1,"height":1},"opacity":1,"edgeAntialiasingMask":251658240,"height":768,"hidden":false,"anchorPoint":{"pointX":0.5,"pointY":0.5}},"layers":[{"animations":[],"initialState":{"affineTransform":[1,0,0,1,0,0],"masksToBounds":false,"rotation":0,"scale":1,"position":{"pointX":512,"pointY":384},"width":1024,"sublayerTransform":[1,0,0,0,0,1,0,0,0,0,1,0,0,0,0,1],"contentsRect":{"y":0,"x":0,"width":1,"height":1},"opacity":1,"edgeAntialiasingMask":251658240,"height":768,"hidden":false,"anchorPoint":{"pointX":0.5,"pointY":0.5}},"layers":[{"animations":[],"layers":[],"texturedRectangle":{"isBackgroundTexture":true,"singleTextureOpacity":1,"textureType":1,"textBaseline":0,"textXHeight":0,"isVerticalText":false},"initialState":{"affineTransform":[1,0,0,1,0,0],"masksToBounds":false,"rotation":0,"scale":1,"position":{"pointX":512,"pointY":384},"width":1024,"sublayerTransform":[1,0,0,0,0,1,0,0,0,0,1,0,0,0,0,1],"contentsRect":{"y":0,"x":0,"width":1,"height":1},"opacity":1,"edgeAntialiasingMask":0,"height":768,"hidden":false,"anchorPoint":{"pointX":0.5,"pointY":0.5}},"texture":"DB8451458D98EFA7506DBEBC2B1323F0"}]}]},{"animations":[],"initialState":{"affineTransform":[1,0,0,1,0,0],"masksToBounds":false,"rotation":0,"scale":1,"position":{"pointX":512,"pointY":384},"width":1024,"sublayerTransform":[1,0,0,0,0,1,0,0,0,0,1,0,0,0,0,1],"contentsRect":{"y":0,"x":0,"width":1,"height":1},"opacity":1,"edgeAntialiasingMask":251658240,"height":768,"hidden":false,"anchorPoint":{"pointX":0.5,"pointY":0.5}},"layers":[{"animations":[],"initialState":{"affineTransform":[1,0,0,1,0,0],"masksToBounds":false,"rotation":0,"scale":1,"position":{"pointX":507,"pointY":90},"width":864,"sublayerTransform":[1,0,0,0,0,1,0,0,0,0,1,0,0,0,0,1],"contentsRect":{"y":0,"x":0,"width":1,"height":1},"opacity":1,"edgeAntialiasingMask":251658240,"height":140,"hidden":false,"anchorPoint":{"pointX":0.5,"pointY":0.5}},"layers":[{"animations":[],"layers":[],"texturedRectangle":{"singleTextureOpacity":1,"textXHeight":0.23634285714285716,"textBaseline":0.90182756696428568,"isBackgroundTexture":true,"isVerticalText":false,"textColor":[0.9999966025352478,0.99999994039535522,0.99999994039535522,1],"textureType":6},"initialState":{"affineTransform":[1,0,0,1,0,0],"masksToBounds":false,"rotation":0,"scale":1,"position":{"pointX":438,"pointY":92},"width":864,"sublayerTransform":[1,0,0,0,0,1,0,0,0,0,1,0,0,0,0,1],"contentsRect":{"y":0,"x":0,"width":1,"height":1},"opacity":1,"edgeAntialiasingMask":0,"height":140,"hidden":false,"anchorPoint":{"pointX":0.5,"pointY":0.5}},"texture":"5B29C2D90D4343C3E8B5BF98D3595A21"}]}]},{"animations":[],"initialState":{"affineTransform":[1,0,0,1,0,0],"masksToBounds":false,"rotation":0,"scale":1,"position":{"pointX":512,"pointY":384},"width":1024,"sublayerTransform":[1,0,0,0,0,1,0,0,0,0,1,0,0,0,0,1],"contentsRect":{"y":0,"x":0,"width":1,"height":1},"opacity":1,"edgeAntialiasingMask":251658240,"height":768,"hidden":false,"anchorPoint":{"pointX":0.5,"pointY":0.5}},"layers":[{"animations":[],"initialState":{"affineTransform":[1,0,0,1,0,0],"masksToBounds":false,"rotation":0,"scale":1,"position":{"pointX":446.5,"pointY":351.5},"width":743,"sublayerTransform":[1,0,0,0,0,1,0,0,0,0,1,0,0,0,0,1],"contentsRect":{"y":0,"x":0,"width":1,"height":1},"opacity":1,"edgeAntialiasingMask":251658240,"height":295,"hidden":false,"anchorPoint":{"pointX":0.5,"pointY":0.5}},"objectID":"F9E39735-38FD-46FE-ACE0-B70E2A7C8901","layers":[{"animations":[],"layers":[],"texturedRectangle":{"singleTextureOpacity":1,"textXHeight":0.30080000000000001,"textBaseline":0.71432883522727275,"isBackgroundTexture":false,"isVerticalText":false,"textColor":[0.9999966025352478,0.99999994039535522,0.99999994039535522,1],"textureType":6},"initialState":{"affineTransform":[1,0,0,1,0,0],"masksToBounds":false,"rotation":0,"scale":1,"position":{"pointX":91.5,"pointY":127.5},"width":175,"sublayerTransform":[1,0,0,0,0,1,0,0,0,0,1,0,0,0,0,1],"contentsRect":{"y":0,"x":0,"width":1,"height":1},"opacity":1,"edgeAntialiasingMask":0,"height":55,"hidden":false,"anchorPoint":{"pointX":0.5,"pointY":0.5}},"texture":"8E39EA93C958539EDD133FF73DC82887"},{"animations":[],"layers":[],"texturedRectangle":{"singleTextureOpacity":1,"textXHeight":0.30080000000000001,"textBaseline":0.71432883522727275,"isBackgroundTexture":false,"isVerticalText":false,"textColor":[0.9999966025352478,0.99999994039535522,0.99999994039535522,1],"textureType":6},"initialState":{"affineTransform":[1,0,0,1,0,0],"masksToBounds":false,"rotation":0,"scale":1,"position":{"pointX":339.5,"pointY":207.5},"width":601,"sublayerTransform":[1,0,0,0,0,1,0,0,0,0,1,0,0,0,0,1],"contentsRect":{"y":0,"x":0,"width":1,"height":1},"opacity":1,"edgeAntialiasingMask":0,"height":55,"hidden":false,"anchorPoint":{"pointX":0.5,"pointY":0.5}},"texture":"74BED5C01827A0250686C62E0B6C4FBC"},{"animations":[],"layers":[],"texturedRectangle":{"singleTextureOpacity":1,"textXHeight":0.30080000000000001,"textBaseline":0.71432883522727275,"isBackgroundTexture":false,"isVerticalText":false,"textColor":[0.9999966025352478,0.99999994039535522,0.99999994039535522,1],"textureType":6},"initialState":{"affineTransform":[1,0,0,1,0,0],"masksToBounds":false,"rotation":0,"scale":1,"position":{"pointX":393,"pointY":287.5},"width":708,"sublayerTransform":[1,0,0,0,0,1,0,0,0,0,1,0,0,0,0,1],"contentsRect":{"y":0,"x":0,"width":1,"height":1},"opacity":1,"edgeAntialiasingMask":0,"height":55,"hidden":true,"anchorPoint":{"pointX":0.5,"pointY":0.5}},"texture":"A7867212BDDC5550EBCA458AE2DD33BC"},{"animations":[],"layers":[],"texturedRectangle":{"singleTextureOpacity":1,"textXHeight":0.30080000000000001,"textBaseline":0.71432883522727275,"isBackgroundTexture":false,"isVerticalText":false,"textColor":[0.9999966025352478,0.99999994039535522,0.99999994039535522,1],"textureType":6},"initialState":{"affineTransform":[1,0,0,1,0,0],"masksToBounds":false,"rotation":0,"scale":1,"position":{"pointX":267,"pointY":367.5},"width":456,"sublayerTransform":[1,0,0,0,0,1,0,0,0,0,1,0,0,0,0,1],"contentsRect":{"y":0,"x":0,"width":1,"height":1},"opacity":1,"edgeAntialiasingMask":0,"height":55,"hidden":true,"anchorPoint":{"pointX":0.5,"pointY":0.5}},"texture":"E919CCB980446EFCFE6CA0B1FA473AF5"}]}]}]}},{"effects":[{"beginTime":0,"baseLayer":{"animations":[],"initialState":{"affineTransform":[1,0,0,1,0,0],"masksToBounds":false,"rotation":0,"scale":1,"position":{"pointX":446.5,"pointY":351.5},"width":743,"sublayerTransform":[1,0,0,0,0,1,0,0,0,0,1,0,0,0,0,1],"contentsRect":{"y":0,"x":0,"width":1,"height":1},"opacity":1,"edgeAntialiasingMask":251658240,"height":295,"hidden":false,"anchorPoint":{"pointX":0.5,"pointY":0.5}},"objectID":"F9E39735-38FD-46FE-ACE0-B70E2A7C8901","layers":[{"animations":[],"layers":[],"texturedRectangle":{"singleTextureOpacity":1,"textXHeight":0.30080000000000001,"textBaseline":0.71432883522727275,"isBackgroundTexture":false,"isVerticalText":false,"textColor":[0.9999966025352478,0.99999994039535522,0.99999994039535522,1],"textureType":6},"initialState":{"affineTransform":[1,0,0,1,0,0],"masksToBounds":false,"rotation":0,"scale":1,"position":{"pointX":91.5,"pointY":127.5},"width":175,"sublayerTransform":[1,0,0,0,0,1,0,0,0,0,1,0,0,0,0,1],"contentsRect":{"y":0,"x":0,"width":1,"height":1},"opacity":1,"edgeAntialiasingMask":0,"height":55,"hidden":false,"anchorPoint":{"pointX":0.5,"pointY":0.5}},"texture":"8E39EA93C958539EDD133FF73DC82887"},{"animations":[],"layers":[],"texturedRectangle":{"singleTextureOpacity":1,"textXHeight":0.30080000000000001,"textBaseline":0.71432883522727275,"isBackgroundTexture":false,"isVerticalText":false,"textColor":[0.9999966025352478,0.99999994039535522,0.99999994039535522,1],"textureType":6},"initialState":{"affineTransform":[1,0,0,1,0,0],"masksToBounds":false,"rotation":0,"scale":1,"position":{"pointX":339.5,"pointY":207.5},"width":601,"sublayerTransform":[1,0,0,0,0,1,0,0,0,0,1,0,0,0,0,1],"contentsRect":{"y":0,"x":0,"width":1,"height":1},"opacity":1,"edgeAntialiasingMask":0,"height":55,"hidden":false,"anchorPoint":{"pointX":0.5,"pointY":0.5}},"texture":"74BED5C01827A0250686C62E0B6C4FBC"},{"animations":[],"layers":[],"texturedRectangle":{"singleTextureOpacity":1,"textXHeight":0.30080000000000001,"textBaseline":0.71432883522727275,"isBackgroundTexture":false,"isVerticalText":false,"textColor":[0.9999966025352478,0.99999994039535522,0.99999994039535522,1],"textureType":6},"initialState":{"affineTransform":[1,0,0,1,0,0],"masksToBounds":false,"rotation":0,"scale":1,"position":{"pointX":393,"pointY":287.5},"width":708,"sublayerTransform":[1,0,0,0,0,1,0,0,0,0,1,0,0,0,0,1],"contentsRect":{"y":0,"x":0,"width":1,"height":1},"opacity":1,"edgeAntialiasingMask":0,"height":55,"hidden":false,"anchorPoint":{"pointX":0.5,"pointY":0.5}},"texture":"A7867212BDDC5550EBCA458AE2DD33BC"},{"animations":[],"initialState":{"affineTransform":[1,0,0,1,0,0],"masksToBounds":false,"rotation":0,"scale":1,"position":{"pointX":437,"pointY":180},"width":743,"sublayerTransform":[1,0,0,0,0,1,0,0,0,0,1,-0.00049229876906403734,0,0,0,1],"contentsRect":{"y":0,"x":0,"width":1,"height":1},"opacity":1,"edgeAntialiasingMask":251658240,"height":295,"hidden":false,"anchorPoint":{"pointX":0.58815612382234184,"pointY":0.61016949152542377}},"layers":[{"animations":[{"timeOffset":0,"from":{"scalar":true},"beginTime":1e-100,"repeatCount":0,"fillMode":"both","property":"hidden","autoreverses":false,"duration":0.01,"to":{"scalar":false}}],"layers":[],"texturedRectangle":{"singleTextureOpacity":1,"textXHeight":0.30080000000000001,"textBaseline":0.71432883522727275,"isBackgroundTexture":false,"isVerticalText":false,"textColor":[0.9999966025352478,0.99999994039535522,0.99999994039535522,1],"textureType":6},"initialState":{"affineTransform":[1,0,0,1,0,0],"masksToBounds":false,"rotation":0,"scale":1,"position":{"pointX":267,"pointY":367.5},"width":456,"sublayerTransform":[1,0,0,0,0,1,0,0,0,0,1,0,0,0,0,1],"contentsRect":{"y":0,"x":0,"width":1,"height":1},"opacity":1,"edgeAntialiasingMask":0,"height":55,"hidden":true,"anchorPoint":{"pointX":0.5,"pointY":0.5}},"texture":"E919CCB980446EFCFE6CA0B1FA473AF5"}]}]},"effects":[],"duration":0.01,"type":"buildIn","name":"apple:appear","objectID":"F9E39735-38FD-46FE-ACE0-B70E2A7C8901"}],"automaticPlay":false,"hyperlinks":[],"accessibility":[{"text":"Ok, so you’re still determined to tamper with blocks.","targetRectangle":{"y":28,"x":80.383999999999901,"width":881.02400000000023,"height":154.1435546875}},{"text":"Checklist:","targetRectangle":{"y":313,"x":114,"width":141.05599999999998,"height":37.10400390625}},{"text":"Fix all the chains (calculate hash codes)","targetRectangle":{"y":351,"x":149,"width":565.98400000000015,"height":79.10400390625}},{"text":"Rebuild the blocks (provide the Proof of Works)","targetRectangle":{"y":431,"x":149,"width":673.24799999999993,"height":79.10400390625}}],"baseLayer":{"animations":[],"initialState":{"affineTransform":[1,0,0,1,0,0],"masksToBounds":false,"rotation":0,"scale":1,"position":{"pointX":512,"pointY":384},"width":1024,"sublayerTransform":[1,0,0,0,0,1,0,0,0,0,1,0,0,0,0,1],"contentsRect":{"y":0,"x":0,"width":1,"height":1},"opacity":1,"edgeAntialiasingMask":251658240,"height":768,"hidden":false,"anchorPoint":{"pointX":0.5,"pointY":0.5}},"layers":[{"animations":[],"initialState":{"affineTransform":[1,0,0,1,0,0],"masksToBounds":false,"rotation":0,"scale":1,"position":{"pointX":512,"pointY":384},"width":1024,"sublayerTransform":[1,0,0,0,0,1,0,0,0,0,1,0,0,0,0,1],"contentsRect":{"y":0,"x":0,"width":1,"height":1},"opacity":1,"edgeAntialiasingMask":251658240,"height":768,"hidden":false,"anchorPoint":{"pointX":0.5,"pointY":0.5}},"layers":[{"animations":[],"initialState":{"affineTransform":[1,0,0,1,0,0],"masksToBounds":false,"rotation":0,"scale":1,"position":{"pointX":512,"pointY":384},"width":1024,"sublayerTransform":[1,0,0,0,0,1,0,0,0,0,1,0,0,0,0,1],"contentsRect":{"y":0,"x":0,"width":1,"height":1},"opacity":1,"edgeAntialiasingMask":251658240,"height":768,"hidden":false,"anchorPoint":{"pointX":0.5,"pointY":0.5}},"layers":[{"animations":[],"layers":[],"texturedRectangle":{"isBackgroundTexture":true,"singleTextureOpacity":1,"textureType":1,"textBaseline":0,"textXHeight":0,"isVerticalText":false},"initialState":{"affineTransform":[1,0,0,1,0,0],"masksToBounds":false,"rotation":0,"scale":1,"position":{"pointX":512,"pointY":384},"width":1024,"sublayerTransform":[1,0,0,0,0,1,0,0,0,0,1,0,0,0,0,1],"contentsRect":{"y":0,"x":0,"width":1,"height":1},"opacity":1,"edgeAntialiasingMask":0,"height":768,"hidden":false,"anchorPoint":{"pointX":0.5,"pointY":0.5}},"texture":"DB8451458D98EFA7506DBEBC2B1323F0"}]}]},{"animations":[],"initialState":{"affineTransform":[1,0,0,1,0,0],"masksToBounds":false,"rotation":0,"scale":1,"position":{"pointX":512,"pointY":384},"width":1024,"sublayerTransform":[1,0,0,0,0,1,0,0,0,0,1,0,0,0,0,1],"contentsRect":{"y":0,"x":0,"width":1,"height":1},"opacity":1,"edgeAntialiasingMask":251658240,"height":768,"hidden":false,"anchorPoint":{"pointX":0.5,"pointY":0.5}},"layers":[{"animations":[],"initialState":{"affineTransform":[1,0,0,1,0,0],"masksToBounds":false,"rotation":0,"scale":1,"position":{"pointX":507,"pointY":90},"width":864,"sublayerTransform":[1,0,0,0,0,1,0,0,0,0,1,0,0,0,0,1],"contentsRect":{"y":0,"x":0,"width":1,"height":1},"opacity":1,"edgeAntialiasingMask":251658240,"height":140,"hidden":false,"anchorPoint":{"pointX":0.5,"pointY":0.5}},"layers":[{"animations":[],"layers":[],"texturedRectangle":{"singleTextureOpacity":1,"textXHeight":0.23634285714285716,"textBaseline":0.90182756696428568,"isBackgroundTexture":true,"isVerticalText":false,"textColor":[0.9999966025352478,0.99999994039535522,0.99999994039535522,1],"textureType":6},"initialState":{"affineTransform":[1,0,0,1,0,0],"masksToBounds":false,"rotation":0,"scale":1,"position":{"pointX":438,"pointY":92},"width":864,"sublayerTransform":[1,0,0,0,0,1,0,0,0,0,1,0,0,0,0,1],"contentsRect":{"y":0,"x":0,"width":1,"height":1},"opacity":1,"edgeAntialiasingMask":0,"height":140,"hidden":false,"anchorPoint":{"pointX":0.5,"pointY":0.5}},"texture":"5B29C2D90D4343C3E8B5BF98D3595A21"}]}]},{"animations":[],"initialState":{"affineTransform":[1,0,0,1,0,0],"masksToBounds":false,"rotation":0,"scale":1,"position":{"pointX":512,"pointY":384},"width":1024,"sublayerTransform":[1,0,0,0,0,1,0,0,0,0,1,0,0,0,0,1],"contentsRect":{"y":0,"x":0,"width":1,"height":1},"opacity":1,"edgeAntialiasingMask":251658240,"height":768,"hidden":false,"anchorPoint":{"pointX":0.5,"pointY":0.5}},"layers":[{"animations":[],"initialState":{"affineTransform":[1,0,0,1,0,0],"masksToBounds":false,"rotation":0,"scale":1,"position":{"pointX":446.5,"pointY":351.5},"width":743,"sublayerTransform":[1,0,0,0,0,1,0,0,0,0,1,0,0,0,0,1],"contentsRect":{"y":0,"x":0,"width":1,"height":1},"opacity":1,"edgeAntialiasingMask":251658240,"height":295,"hidden":false,"anchorPoint":{"pointX":0.5,"pointY":0.5}},"objectID":"F9E39735-38FD-46FE-ACE0-B70E2A7C8901","layers":[{"animations":[],"layers":[],"texturedRectangle":{"singleTextureOpacity":1,"textXHeight":0.30080000000000001,"textBaseline":0.71432883522727275,"isBackgroundTexture":false,"isVerticalText":false,"textColor":[0.9999966025352478,0.99999994039535522,0.99999994039535522,1],"textureType":6},"initialState":{"affineTransform":[1,0,0,1,0,0],"masksToBounds":false,"rotation":0,"scale":1,"position":{"pointX":91.5,"pointY":127.5},"width":175,"sublayerTransform":[1,0,0,0,0,1,0,0,0,0,1,0,0,0,0,1],"contentsRect":{"y":0,"x":0,"width":1,"height":1},"opacity":1,"edgeAntialiasingMask":0,"height":55,"hidden":false,"anchorPoint":{"pointX":0.5,"pointY":0.5}},"texture":"8E39EA93C958539EDD133FF73DC82887"},{"animations":[],"layers":[],"texturedRectangle":{"singleTextureOpacity":1,"textXHeight":0.30080000000000001,"textBaseline":0.71432883522727275,"isBackgroundTexture":false,"isVerticalText":false,"textColor":[0.9999966025352478,0.99999994039535522,0.99999994039535522,1],"textureType":6},"initialState":{"affineTransform":[1,0,0,1,0,0],"masksToBounds":false,"rotation":0,"scale":1,"position":{"pointX":339.5,"pointY":207.5},"width":601,"sublayerTransform":[1,0,0,0,0,1,0,0,0,0,1,0,0,0,0,1],"contentsRect":{"y":0,"x":0,"width":1,"height":1},"opacity":1,"edgeAntialiasingMask":0,"height":55,"hidden":false,"anchorPoint":{"pointX":0.5,"pointY":0.5}},"texture":"74BED5C01827A0250686C62E0B6C4FBC"},{"animations":[],"layers":[],"texturedRectangle":{"singleTextureOpacity":1,"textXHeight":0.30080000000000001,"textBaseline":0.71432883522727275,"isBackgroundTexture":false,"isVerticalText":false,"textColor":[0.9999966025352478,0.99999994039535522,0.99999994039535522,1],"textureType":6},"initialState":{"affineTransform":[1,0,0,1,0,0],"masksToBounds":false,"rotation":0,"scale":1,"position":{"pointX":393,"pointY":287.5},"width":708,"sublayerTransform":[1,0,0,0,0,1,0,0,0,0,1,0,0,0,0,1],"contentsRect":{"y":0,"x":0,"width":1,"height":1},"opacity":1,"edgeAntialiasingMask":0,"height":55,"hidden":false,"anchorPoint":{"pointX":0.5,"pointY":0.5}},"texture":"A7867212BDDC5550EBCA458AE2DD33BC"},{"animations":[],"layers":[],"texturedRectangle":{"singleTextureOpacity":1,"textXHeight":0.30080000000000001,"textBaseline":0.71432883522727275,"isBackgroundTexture":false,"isVerticalText":false,"textColor":[0.9999966025352478,0.99999994039535522,0.99999994039535522,1],"textureType":6},"initialState":{"affineTransform":[1,0,0,1,0,0],"masksToBounds":false,"rotation":0,"scale":1,"position":{"pointX":267,"pointY":367.5},"width":456,"sublayerTransform":[1,0,0,0,0,1,0,0,0,0,1,0,0,0,0,1],"contentsRect":{"y":0,"x":0,"width":1,"height":1},"opacity":1,"edgeAntialiasingMask":0,"height":55,"hidden":true,"anchorPoint":{"pointX":0.5,"pointY":0.5}},"texture":"E919CCB980446EFCFE6CA0B1FA473AF5"}]}]}]}},{"effects":[{"beginTime":0,"baseLayer":{"animations":[],"initialState":{"affineTransform":[1,0,0,1,0,0],"masksToBounds":false,"rotation":0,"scale":1,"position":{"pointX":512,"pointY":384},"width":1024,"sublayerTransform":[1,0,0,0,0,1,0,0,0,0,1,0,0,0,0,1],"contentsRect":{"y":0,"x":0,"width":1,"height":1},"opacity":1,"edgeAntialiasingMask":251658240,"height":768,"hidden":false,"anchorPoint":{"pointX":0.5,"pointY":0.5}},"objectID":"0","layers":[{"animations":[],"initialState":{"affineTransform":[1,0,0,1,0,0],"masksToBounds":false,"rotation":0,"scale":1,"position":{"pointX":512,"pointY":384},"width":1024,"sublayerTransform":[1,0,0,0,0,1,0,0,0,0,1,-0.00049229876906403734,0,0,0,1],"contentsRect":{"y":0,"x":0,"width":1,"height":1},"opacity":1,"edgeAntialiasingMask":251658240,"height":768,"hidden":false,"anchorPoint":{"pointX":0.5,"pointY":0.5}},"layers":[{"animations":[],"layers":[],"texturedRectangle":{"isBackgroundTexture":false,"singleTextureOpacity":1,"textureType":0,"textBaseline":0,"textXHeight":0,"isVerticalText":false},"initialState":{"affineTransform":[1,0,0,1,0,0],"masksToBounds":false,"rotation":0,"scale":1,"position":{"pointX":512,"pointY":384},"width":1024,"sublayerTransform":[1,0,0,0,0,1,0,0,0,0,1,0,0,0,0,1],"contentsRect":{"y":0,"x":0,"width":1,"height":1},"opacity":1,"edgeAntialiasingMask":0,"height":768,"hidden":false,"anchorPoint":{"pointX":0.5,"pointY":0.5}},"texture":"7BA44EE4C83848934E09B512DF4E5631"},{"animations":[{"timeOffset":0,"from":{"scalar":false},"beginTime":0,"repeatCount":0,"fillMode":"both","property":"hidden","autoreverses":false,"duration":0.01,"to":{"scalar":true}}],"layers":[],"texturedRectangle":{"isBackgroundTexture":false,"singleTextureOpacity":1,"textureType":0,"textBaseline":0,"textXHeight":0,"isVerticalText":false},"initialState":{"affineTransform":[1,0,0,1,0,0],"masksToBounds":false,"rotation":0,"scale":1,"position":{"pointX":512,"pointY":384},"width":1024,"sublayerTransform":[1,0,0,0,0,1,0,0,0,0,1,0,0,0,0,1],"contentsRect":{"y":0,"x":0,"width":1,"height":1},"opacity":1,"edgeAntialiasingMask":0,"height":768,"hidden":false,"anchorPoint":{"pointX":0.5,"pointY":0.5}},"texture":"C57C769CF9D7B954C9ABBCAAAD5B84D8"}]}]},"effects":[],"duration":0.01,"type":"transition","name":"none","objectID":"0"}],"automaticPlay":false,"hyperlinks":[],"accessibility":[{"text":"Ok, so you’re still determined to tamper with blocks.","targetRectangle":{"y":28,"x":80.383999999999901,"width":881.02400000000023,"height":154.1435546875}},{"text":"Checklist:","targetRectangle":{"y":313,"x":114,"width":141.05599999999998,"height":37.10400390625}},{"text":"Fix all the chains (calculate hash codes)","targetRectangle":{"y":351,"x":149,"width":565.98400000000015,"height":79.10400390625}},{"text":"Rebuild the blocks (provide the Proof of Works)","targetRectangle":{"y":431,"x":149,"width":673.24799999999993,"height":79.10400390625}},{"text":"Take over >50% of the nodes","targetRectangle":{"y":511,"x":149,"width":420.48000000000002,"height":79.10400390625}}],"baseLayer":{"animations":[],"initialState":{"affineTransform":[1,0,0,1,0,0],"masksToBounds":false,"rotation":0,"scale":1,"position":{"pointX":512,"pointY":384},"width":1024,"sublayerTransform":[1,0,0,0,0,1,0,0,0,0,1,0,0,0,0,1],"contentsRect":{"y":0,"x":0,"width":1,"height":1},"opacity":1,"edgeAntialiasingMask":251658240,"height":768,"hidden":false,"anchorPoint":{"pointX":0.5,"pointY":0.5}},"objectID":"0","layers":[{"animations":[],"initialState":{"affineTransform":[1,0,0,1,0,0],"masksToBounds":false,"rotation":0,"scale":1,"position":{"pointX":512,"pointY":384},"width":1024,"sublayerTransform":[1,0,0,0,0,1,0,0,0,0,1,-0.00049229876906403734,0,0,0,1],"contentsRect":{"y":0,"x":0,"width":1,"height":1},"opacity":1,"edgeAntialiasingMask":251658240,"height":768,"hidden":false,"anchorPoint":{"pointX":0.5,"pointY":0.5}},"layers":[{"animations":[],"layers":[],"texturedRectangle":{"isBackgroundTexture":false,"singleTextureOpacity":1,"textureType":0,"textBaseline":0,"textXHeight":0,"isVerticalText":false},"initialState":{"affineTransform":[1,0,0,1,0,0],"masksToBounds":false,"rotation":0,"scale":1,"position":{"pointX":512,"pointY":384},"width":1024,"sublayerTransform":[1,0,0,0,0,1,0,0,0,0,1,0,0,0,0,1],"contentsRect":{"y":0,"x":0,"width":1,"height":1},"opacity":1,"edgeAntialiasingMask":0,"height":768,"hidden":false,"anchorPoint":{"pointX":0.5,"pointY":0.5}},"texture":"C57C769CF9D7B954C9ABBCAAAD5B84D8"}]}]}}]}